discrete_pmf/__init__.py
discrete_pmf/core.py
discrete_pmf-0.1.4.dist-info/METADATA
discrete_pmf-0.1.4.dist-info/WHEEL
discrete_pmf-0.1.4.dist-info/RECORD
