Metadata-Version: 2.3
Name: discrete_pmf
Version: 0.1.4
Summary: Compute and plot PMFs for Binomial, Geometric, Negative Binomial and Poisson distributions.
Author: Nana-Ansah-Adomako
Author-email: nanaadomakoansah@gmail.com
Requires-Python: >=3.12,<4.0
Classifier: Programming Language :: Python :: 3
Classifier: Programming Language :: Python :: 3.12
Classifier: Programming Language :: Python :: 3.13
Requires-Dist: matplotlib (>=3.5,<4.0)
